eatnyc/__init__.py
eatnyc/__main__.py
eatnyc/core.py
eatnyc/data/nyc_restaurant_data.csv
eatnyc-0.1.2.dist-info/licenses/LICENSE
eatnyc-0.1.2.dist-info/METADATA
eatnyc-0.1.2.dist-info/WHEEL
eatnyc-0.1.2.dist-info/entry_points.txt
eatnyc-0.1.2.dist-info/top_level.txt
eatnyc-0.1.2.dist-info/RECORD
