Metadata-Version: 2.4
Name: eatnyc
Version: 0.1.2
Summary: A tiny NYC restaurant recommender near NYU.
Author: Team Avalon
License: MIT
Project-URL: Homepage, https://github.com/swe-students-fall2025/3-python-package-team_avalon
Project-URL: Issues, https://github.com/swe-students-fall2025/3-python-package-team_avalon/issues
Keywords: nyc,restaurants,fun,food,recommendations
Classifier: Programming Language :: Python :: 3
Classifier: License :: OSI Approved :: MIT License
Classifier: Operating System :: OS Independent
Requires-Python: >=3.10
License-File: LICENSE
Dynamic: license-file
